[{"bounds":{"X":2350,"Y":-50,"Width":50,"Height":50},"type":2},{"bounds":{"X":2350,"Y":0,"Width":50,"Height":50},"type":2},{"bounds":{"X":2700,"Y":-50,"Width":50,"Height":50},"type":2},{"bounds":{"X":2650,"Y":0,"Width":50,"Height":50},"type":2},{"bounds":{"X":2100,"Y":100,"Width":50,"Height":50},"type":2},{"bounds":{"X":2450,"Y":300,"Width":50,"Height":50},"type":2},{"bounds":{"X":0,"Y":800,"Width":50,"Height":50},"type":2},{"bounds":{"X":50,"Y":800,"Width":50,"Height":50},"type":2},{"bounds":{"X":100,"Y":800,"Width":50,"Height":50},"type":2},{"bounds":{"X":200,"Y":800,"Width":50,"Height":50},"type":2},{"bounds":{"X":150,"Y":800,"Width":50,"Height":50},"type":2},{"bounds":{"X":250,"Y":800,"Width":50,"Height":50},"type":2},{"bounds":{"X":300,"Y":800,"Width":50,"Height":50},"type":2},{"bounds":{"X":350,"Y":800,"Width":50,"Height":50},"type":2},{"bounds":{"X":200,"Y":950,"Width":50,"Height":50},"type":2},{"bounds":{"X":250,"Y":950,"Width":50,"Height":50},"type":2},{"bounds":{"X":300,"Y":950,"Width":50,"Height":50},"type":2},{"bounds":{"X":350,"Y":950,"Width":50,"Height":50},"type":2},{"bounds":{"X":400,"Y":950,"Width":50,"Height":50},"type":2},{"bounds":{"X":500,"Y":950,"Width":50,"Height":50},"type":2},{"bounds":{"X":450,"Y":950,"Width":50,"Height":50},"type":2},{"bounds":{"X":550,"Y":950,"Width":50,"Height":50},"type":2},{"bounds":{"X":600,"Y":950,"Width":50,"Height":50},"type":2},{"bounds":{"X":650,"Y":950,"Width":50,"Height":50},"type":2},{"bounds":{"X":700,"Y":950,"Width":50,"Height":50},"type":2},{"bounds":{"X":750,"Y":950,"Width":50,"Height":50},"type":2},{"bounds":{"X":850,"Y":950,"Width":50,"Height":50},"type":2},{"bounds":{"X":800,"Y":950,"Width":50,"Height":50},"type":2},{"bounds":{"X":900,"Y":950,"Width":50,"Height":50},"type":2},{"bounds":{"X":1000,"Y":950,"Width":50,"Height":50},"type":2},{"bounds":{"X":950,"Y":950,"Width":50,"Height":50},"type":2},{"bounds":{"X":200,"Y":900,"Width":50,"Height":50},"type":1},{"bounds":{"X":250,"Y":900,"Width":50,"Height":50},"type":1},{"bounds":{"X":300,"Y":900,"Width":50,"Height":50},"type":1},{"bounds":{"X":400,"Y":900,"Width":50,"Height":50},"type":1},{"bounds":{"X":350,"Y":900,"Width":50,"Height":50},"type":1},{"bounds":{"X":450,"Y":900,"Width":50,"Height":50},"type":1},{"bounds":{"X":500,"Y":900,"Width":50,"Height":50},"type":1},{"bounds":{"X":550,"Y":900,"Width":50,"Height":50},"type":1},{"bounds":{"X":600,"Y":900,"Width":50,"Height":50},"type":1},{"bounds":{"X":650,"Y":900,"Width":50,"Height":50},"type":1},{"bounds":{"X":700,"Y":900,"Width":50,"Height":50},"type":1},{"bounds":{"X":750,"Y":900,"Width":50,"Height":50},"type":1},{"bounds":{"X":800,"Y":900,"Width":50,"Height":50},"type":1},{"bounds":{"X":850,"Y":900,"Width":50,"Height":50},"type":1},{"bounds":{"X":900,"Y":900,"Width":50,"Height":50},"type":1},{"bounds":{"X":950,"Y":900,"Width":50,"Height":50},"type":1},{"bounds":{"X":1000,"Y":900,"Width":50,"Height":50},"type":1},{"bounds":{"X":350,"Y":750,"Width":50,"Height":50},"type":1},{"bounds":{"X":300,"Y":750,"Width":50,"Height":50},"type":1},{"bounds":{"X":250,"Y":750,"Width":50,"Height":50},"type":1},{"bounds":{"X":200,"Y":750,"Width":50,"Height":50},"type":1},{"bounds":{"X":150,"Y":750,"Width":50,"Height":50},"type":1},{"bounds":{"X":100,"Y":750,"Width":50,"Height":50},"type":1},{"bounds":{"X":50,"Y":750,"Width":50,"Height":50},"type":1},{"bounds":{"X":0,"Y":750,"Width":50,"Height":50},"type":1},{"bounds":{"X":1200,"Y":950,"Width":50,"Height":50},"type":2},{"bounds":{"X":1300,"Y":950,"Width":50,"Height":50},"type":2},{"bounds":{"X":1350,"Y":950,"Width":50,"Height":50},"type":2},{"bounds":{"X":1250,"Y":950,"Width":50,"Height":50},"type":2},{"bounds":{"X":1400,"Y":950,"Width":50,"Height":50},"type":2},{"bounds":{"X":1450,"Y":950,"Width":50,"Height":50},"type":2},{"bounds":{"X":1500,"Y":950,"Width":50,"Height":50},"type":2},{"bounds":{"X":1550,"Y":950,"Width":50,"Height":50},"type":2},{"bounds":{"X":1600,"Y":950,"Width":50,"Height":50},"type":2},{"bounds":{"X":1650,"Y":950,"Width":50,"Height":50},"type":2},{"bounds":{"X":1700,"Y":950,"Width":50,"Height":50},"type":2},{"bounds":{"X":1750,"Y":950,"Width":50,"Height":50},"type":2},{"bounds":{"X":1800,"Y":950,"Width":50,"Height":50},"type":2},{"bounds":{"X":1850,"Y":950,"Width":50,"Height":50},"type":2},{"bounds":{"X":1900,"Y":950,"Width":50,"Height":50},"type":2},{"bounds":{"X":1200,"Y":900,"Width":50,"Height":50},"type":1},{"bounds":{"X":1250,"Y":900,"Width":50,"Height":50},"type":1},{"bounds":{"X":1300,"Y":900,"Width":50,"Height":50},"type":1},{"bounds":{"X":1350,"Y":900,"Width":50,"Height":50},"type":1},{"bounds":{"X":1400,"Y":900,"Width":50,"Height":50},"type":1},{"bounds":{"X":1450,"Y":900,"Width":50,"Height":50},"type":1},{"bounds":{"X":1500,"Y":900,"Width":50,"Height":50},"type":1},{"bounds":{"X":1550,"Y":900,"Width":50,"Height":50},"type":1},{"bounds":{"X":1600,"Y":900,"Width":50,"Height":50},"type":1},{"bounds":{"X":1650,"Y":900,"Width":50,"Height":50},"type":1},{"bounds":{"X":1700,"Y":900,"Width":50,"Height":50},"type":1},{"bounds":{"X":1750,"Y":900,"Width":50,"Height":50},"type":1},{"bounds":{"X":1800,"Y":900,"Width":50,"Height":50},"type":1},{"bounds":{"X":1850,"Y":900,"Width":50,"Height":50},"type":1},{"bounds":{"X":1900,"Y":900,"Width":50,"Height":50},"type":1},{"bounds":{"X":450,"Y":600,"Width":50,"Height":50},"type":1},{"bounds":{"X":500,"Y":600,"Width":50,"Height":50},"type":1},{"bounds":{"X":550,"Y":600,"Width":50,"Height":50},"type":1},{"bounds":{"X":600,"Y":600,"Width":50,"Height":50},"type":1},{"bounds":{"X":650,"Y":600,"Width":50,"Height":50},"type":1},{"bounds":{"X":750,"Y":600,"Width":50,"Height":50},"type":1},{"bounds":{"X":700,"Y":600,"Width":50,"Height":50},"type":1},{"bounds":{"X":800,"Y":600,"Width":50,"Height":50},"type":1},{"bounds":{"X":450,"Y":650,"Width":50,"Height":50},"type":2},{"bounds":{"X":500,"Y":650,"Width":50,"Height":50},"type":2},{"bounds":{"X":550,"Y":650,"Width":50,"Height":50},"type":2},{"bounds":{"X":600,"Y":650,"Width":50,"Height":50},"type":2},{"bounds":{"X":650,"Y":650,"Width":50,"Height":50},"type":2},{"bounds":{"X":700,"Y":650,"Width":50,"Height":50},"type":2},{"bounds":{"X":750,"Y":650,"Width":50,"Height":50},"type":2},{"bounds":{"X":800,"Y":650,"Width":50,"Height":50},"type":2},{"bounds":{"X":300,"Y":450,"Width":50,"Height":50},"type":2},{"bounds":{"X":250,"Y":450,"Width":50,"Height":50},"type":2},{"bounds":{"X":200,"Y":450,"Width":50,"Height":50},"type":2},{"bounds":{"X":150,"Y":450,"Width":50,"Height":50},"type":2},{"bounds":{"X":100,"Y":450,"Width":50,"Height":50},"type":2},{"bounds":{"X":50,"Y":450,"Width":50,"Height":50},"type":2},{"bounds":{"X":0,"Y":450,"Width":50,"Height":50},"type":2},{"bounds":{"X":0,"Y":400,"Width":50,"Height":50},"type":1},{"bounds":{"X":50,"Y":400,"Width":50,"Height":50},"type":1},{"bounds":{"X":100,"Y":400,"Width":50,"Height":50},"type":1},{"bounds":{"X":150,"Y":400,"Width":50,"Height":50},"type":1},{"bounds":{"X":200,"Y":400,"Width":50,"Height":50},"type":1},{"bounds":{"X":250,"Y":400,"Width":50,"Height":50},"type":1},{"bounds":{"X":300,"Y":400,"Width":50,"Height":50},"type":1},{"bounds":{"X":400,"Y":300,"Width":50,"Height":50},"type":2},{"bounds":{"X":450,"Y":300,"Width":50,"Height":50},"type":2},{"bounds":{"X":500,"Y":300,"Width":50,"Height":50},"type":2},{"bounds":{"X":550,"Y":300,"Width":50,"Height":50},"type":2},{"bounds":{"X":600,"Y":300,"Width":50,"Height":50},"type":2},{"bounds":{"X":650,"Y":300,"Width":50,"Height":50},"type":2},{"bounds":{"X":400,"Y":250,"Width":50,"Height":50},"type":1},{"bounds":{"X":450,"Y":250,"Width":50,"Height":50},"type":1},{"bounds":{"X":500,"Y":250,"Width":50,"Height":50},"type":1},{"bounds":{"X":550,"Y":250,"Width":50,"Height":50},"type":1},{"bounds":{"X":600,"Y":250,"Width":50,"Height":50},"type":1},{"bounds":{"X":650,"Y":250,"Width":50,"Height":50},"type":1},{"bounds":{"X":50,"Y":100,"Width":50,"Height":50},"type":1},{"bounds":{"X":150,"Y":100,"Width":50,"Height":50},"type":1},{"bounds":{"X":100,"Y":100,"Width":50,"Height":50},"type":1},{"bounds":{"X":200,"Y":100,"Width":50,"Height":50},"type":1},{"bounds":{"X":250,"Y":100,"Width":50,"Height":50},"type":1},{"bounds":{"X":50,"Y":150,"Width":50,"Height":50},"type":2},{"bounds":{"X":100,"Y":150,"Width":50,"Height":50},"type":2},{"bounds":{"X":150,"Y":150,"Width":50,"Height":50},"type":2},{"bounds":{"X":200,"Y":150,"Width":50,"Height":50},"type":2},{"bounds":{"X":250,"Y":150,"Width":50,"Height":50},"type":2},{"bounds":{"X":1350,"Y":450,"Width":50,"Height":50},"type":1},{"bounds":{"X":1300,"Y":500,"Width":50,"Height":50},"type":1},{"bounds":{"X":1250,"Y":550,"Width":50,"Height":50},"type":1},{"bounds":{"X":1200,"Y":600,"Width":50,"Height":50},"type":1},{"bounds":{"X":1150,"Y":650,"Width":50,"Height":50},"type":1},{"bounds":{"X":1400,"Y":500,"Width":50,"Height":50},"type":1},{"bounds":{"X":1450,"Y":550,"Width":50,"Height":50},"type":1},{"bounds":{"X":1500,"Y":600,"Width":50,"Height":50},"type":1},{"bounds":{"X":1550,"Y":650,"Width":50,"Height":50},"type":1},{"bounds":{"X":1600,"Y":700,"Width":50,"Height":50},"type":1},{"bounds":{"X":1100,"Y":700,"Width":50,"Height":50},"type":1},{"bounds":{"X":1050,"Y":750,"Width":50,"Height":50},"type":1},{"bounds":{"X":1650,"Y":750,"Width":50,"Height":50},"type":1},{"bounds":{"X":1100,"Y":750,"Width":50,"Height":50},"type":2},{"bounds":{"X":1150,"Y":700,"Width":50,"Height":50},"type":2},{"bounds":{"X":1200,"Y":650,"Width":50,"Height":50},"type":2},{"bounds":{"X":1250,"Y":600,"Width":50,"Height":50},"type":2},{"bounds":{"X":1300,"Y":550,"Width":50,"Height":50},"type":2},{"bounds":{"X":1350,"Y":500,"Width":50,"Height":50},"type":2},{"bounds":{"X":1350,"Y":550,"Width":50,"Height":50},"type":2},{"bounds":{"X":1400,"Y":550,"Width":50,"Height":50},"type":2},{"bounds":{"X":1450,"Y":600,"Width":50,"Height":50},"type":2},{"bounds":{"X":1500,"Y":650,"Width":50,"Height":50},"type":2},{"bounds":{"X":1550,"Y":700,"Width":50,"Height":50},"type":2},{"bounds":{"X":1600,"Y":750,"Width":50,"Height":50},"type":2},{"bounds":{"X":1300,"Y":750,"Width":50,"Height":50},"type":2},{"bounds":{"X":1350,"Y":750,"Width":50,"Height":50},"type":2},{"bounds":{"X":1400,"Y":750,"Width":50,"Height":50},"type":2},{"bounds":{"X":1400,"Y":700,"Width":50,"Height":50},"type":1},{"bounds":{"X":1350,"Y":700,"Width":50,"Height":50},"type":1},{"bounds":{"X":1300,"Y":700,"Width":50,"Height":50},"type":1},{"bounds":{"X":3050,"Y":150,"Width":50,"Height":50},"type":2},{"bounds":{"X":1500,"Y":350,"Width":50,"Height":50},"type":2},{"bounds":{"X":1900,"Y":300,"Width":50,"Height":50},"type":2},{"bounds":{"X":1900,"Y":250,"Width":50,"Height":50},"type":2},{"bounds":{"X":1900,"Y":200,"Width":50,"Height":50},"type":2},{"bounds":{"X":1900,"Y":150,"Width":50,"Height":50},"type":2},{"bounds":{"X":1850,"Y":100,"Width":50,"Height":50},"type":2},{"bounds":{"X":1900,"Y":100,"Width":50,"Height":50},"type":2},{"bounds":{"X":1800,"Y":100,"Width":50,"Height":50},"type":2},{"bounds":{"X":1750,"Y":100,"Width":50,"Height":50},"type":2},{"bounds":{"X":1650,"Y":100,"Width":50,"Height":50},"type":2},{"bounds":{"X":1700,"Y":100,"Width":50,"Height":50},"type":2},{"bounds":{"X":1600,"Y":100,"Width":50,"Height":50},"type":2},{"bounds":{"X":1550,"Y":100,"Width":50,"Height":50},"type":2},{"bounds":{"X":1500,"Y":100,"Width":50,"Height":50},"type":2},{"bounds":{"X":1450,"Y":100,"Width":50,"Height":50},"type":2},{"bounds":{"X":1450,"Y":150,"Width":50,"Height":50},"type":2},{"bounds":{"X":1450,"Y":200,"Width":50,"Height":50},"type":2},{"bounds":{"X":1400,"Y":200,"Width":50,"Height":50},"type":2},{"bounds":{"X":1350,"Y":200,"Width":50,"Height":50},"type":2},{"bounds":{"X":1300,"Y":200,"Width":50,"Height":50},"type":2},{"bounds":{"X":1250,"Y":200,"Width":50,"Height":50},"type":2},{"bounds":{"X":1250,"Y":250,"Width":50,"Height":50},"type":2},{"bounds":{"X":1250,"Y":300,"Width":50,"Height":50},"type":2},{"bounds":{"X":1250,"Y":350,"Width":50,"Height":50},"type":2},{"bounds":{"X":1250,"Y":150,"Width":50,"Height":50},"type":1},{"bounds":{"X":1300,"Y":150,"Width":50,"Height":50},"type":1},{"bounds":{"X":1350,"Y":150,"Width":50,"Height":50},"type":1},{"bounds":{"X":1400,"Y":150,"Width":50,"Height":50},"type":1},{"bounds":{"X":1400,"Y":100,"Width":50,"Height":50},"type":1},{"bounds":{"X":1400,"Y":50,"Width":50,"Height":50},"type":1},{"bounds":{"X":1450,"Y":50,"Width":50,"Height":50},"type":1},{"bounds":{"X":1500,"Y":50,"Width":50,"Height":50},"type":1},{"bounds":{"X":1550,"Y":50,"Width":50,"Height":50},"type":1},{"bounds":{"X":1600,"Y":50,"Width":50,"Height":50},"type":1},{"bounds":{"X":1650,"Y":50,"Width":50,"Height":50},"type":1},{"bounds":{"X":1700,"Y":50,"Width":50,"Height":50},"type":1},{"bounds":{"X":1750,"Y":50,"Width":50,"Height":50},"type":1},{"bounds":{"X":1800,"Y":50,"Width":50,"Height":50},"type":1},{"bounds":{"X":1850,"Y":50,"Width":50,"Height":50},"type":1},{"bounds":{"X":1900,"Y":50,"Width":50,"Height":50},"type":1},{"bounds":{"X":1100,"Y":150,"Width":50,"Height":50},"type":1},{"bounds":{"X":1050,"Y":150,"Width":50,"Height":50},"type":1},{"bounds":{"X":1000,"Y":150,"Width":50,"Height":50},"type":1},{"bounds":{"X":950,"Y":150,"Width":50,"Height":50},"type":1},{"bounds":{"X":900,"Y":150,"Width":50,"Height":50},"type":1},{"bounds":{"X":900,"Y":200,"Width":50,"Height":50},"type":2},{"bounds":{"X":950,"Y":200,"Width":50,"Height":50},"type":2},{"bounds":{"X":1000,"Y":200,"Width":50,"Height":50},"type":2},{"bounds":{"X":1100,"Y":200,"Width":50,"Height":50},"type":2},{"bounds":{"X":1050,"Y":200,"Width":50,"Height":50},"type":2},{"bounds":{"X":1200,"Y":300,"Width":50,"Height":50},"type":1},{"bounds":{"X":1150,"Y":300,"Width":50,"Height":50},"type":1},{"bounds":{"X":1100,"Y":450,"Width":50,"Height":50},"type":1},{"bounds":{"X":1050,"Y":450,"Width":50,"Height":50},"type":1},{"bounds":{"X":1000,"Y":450,"Width":50,"Height":50},"type":1},{"bounds":{"X":950,"Y":450,"Width":50,"Height":50},"type":1},{"bounds":{"X":950,"Y":500,"Width":50,"Height":50},"type":2},{"bounds":{"X":1000,"Y":500,"Width":50,"Height":50},"type":2},{"bounds":{"X":1050,"Y":500,"Width":50,"Height":50},"type":2},{"bounds":{"X":1100,"Y":500,"Width":50,"Height":50},"type":2},{"bounds":{"X":1400,"Y":350,"Width":50,"Height":50},"type":1},{"bounds":{"X":1450,"Y":350,"Width":50,"Height":50},"type":1},{"bounds":{"X":1500,"Y":300,"Width":50,"Height":50},"type":1},{"bounds":{"X":1550,"Y":300,"Width":50,"Height":50},"type":1},{"bounds":{"X":1600,"Y":300,"Width":50,"Height":50},"type":1},{"bounds":{"X":1650,"Y":300,"Width":50,"Height":50},"type":1},{"bounds":{"X":1700,"Y":300,"Width":50,"Height":50},"type":1},{"bounds":{"X":1750,"Y":300,"Width":50,"Height":50},"type":1},{"bounds":{"X":1800,"Y":300,"Width":50,"Height":50},"type":1},{"bounds":{"X":1850,"Y":300,"Width":50,"Height":50},"type":1},{"bounds":{"X":1600,"Y":350,"Width":50,"Height":50},"type":2},{"bounds":{"X":1650,"Y":350,"Width":50,"Height":50},"type":2},{"bounds":{"X":1750,"Y":350,"Width":50,"Height":50},"type":2},{"bounds":{"X":1800,"Y":350,"Width":50,"Height":50},"type":2},{"bounds":{"X":1700,"Y":350,"Width":50,"Height":50},"type":2},{"bounds":{"X":1850,"Y":350,"Width":50,"Height":50},"type":2},{"bounds":{"X":1900,"Y":350,"Width":50,"Height":50},"type":2},{"bounds":{"X":1550,"Y":350,"Width":50,"Height":50},"type":2},{"bounds":{"X":1600,"Y":250,"Width":50,"Height":50},"type":3},{"bounds":{"X":1350,"Y":100,"Width":50,"Height":50},"type":3},{"bounds":{"X":1750,"Y":0,"Width":50,"Height":50},"type":3},{"bounds":{"X":1500,"Y":0,"Width":50,"Height":50},"type":3},{"bounds":{"X":1050,"Y":100,"Width":50,"Height":50},"type":3},{"bounds":{"X":950,"Y":100,"Width":50,"Height":50},"type":3},{"bounds":{"X":550,"Y":200,"Width":50,"Height":50},"type":3},{"bounds":{"X":100,"Y":350,"Width":50,"Height":50},"type":3},{"bounds":{"X":250,"Y":350,"Width":50,"Height":50},"type":3},{"bounds":{"X":150,"Y":50,"Width":50,"Height":50},"type":3},{"bounds":{"X":0,"Y":700,"Width":50,"Height":50},"type":3},{"bounds":{"X":1850,"Y":250,"Width":50,"Height":50},"type":3},{"bounds":{"X":1900,"Y":0,"Width":50,"Height":50},"type":3},{"bounds":{"X":550,"Y":550,"Width":50,"Height":50},"type":3},{"bounds":{"X":750,"Y":550,"Width":50,"Height":50},"type":3},{"bounds":{"X":1050,"Y":400,"Width":50,"Height":50},"type":3},{"bounds":{"X":1350,"Y":650,"Width":50,"Height":50},"type":3},{"bounds":{"X":1800,"Y":850,"Width":50,"Height":50},"type":3},{"bounds":{"X":1400,"Y":850,"Width":50,"Height":50},"type":3},{"bounds":{"X":750,"Y":850,"Width":50,"Height":50},"type":3},{"bounds":{"X":400,"Y":850,"Width":50,"Height":50},"type":3},{"bounds":{"X":200,"Y":700,"Width":50,"Height":50},"type":0}]
